geearea/__init__.py
geearea/area.py
geearea-0.1.0.dist-info/LICENSE
geearea-0.1.0.dist-info/METADATA
geearea-0.1.0.dist-info/WHEEL
geearea-0.1.0.dist-info/top_level.txt
geearea-0.1.0.dist-info/RECORD
