Metadata-Version: 2.1
Name: geearea
Version: 0.1.0
Summary: Managing GEE data easily
Home-page: UNKNOWN
Author: Jon Rosario
Author-email: <jonf.rosario@gmail.com>
License: UNKNOWN
Keywords: python,google earth engine,gee,area
Platform: UNKNOWN
Classifier: Development Status :: 5 - Production/Stable
Classifier: Topic :: Utilities
Classifier: License :: OSI Approved :: MIT License
Requires-Dist: folium
Requires-Dist: earthengine-api
Requires-Dist: matplotlib
Requires-Dist: numpy
